configchain/__init__.py
configchain/config.py
configchain/configset.py
configchain/loader.py
configchain/parser.py
configchain/snippet.py
configchain/source.py
configchain/types.py
configchain/utils.py
configchain-0.3.12.dist-info/LICENSE
configchain-0.3.12.dist-info/METADATA
configchain-0.3.12.dist-info/WHEEL
configchain-0.3.12.dist-info/top_level.txt
configchain-0.3.12.dist-info/RECORD
